{
    "relevance": 0.6094648897403386,
    "sdgs": [
        {
            "sdg": 1,
            "importance": 0.27264228133660223,
            "category": "medium",
            "features": [
                "poverty reduction",
                "number people",
                "extreme poverty",
                "poverty line",
                "growth poverty",
                "poverty alleviation",
                "health care",
                "social protection",
                "poverty eradication",
                "distributional effect",
                "absolute poverty",
                "woman work",
                "live extreme poverty",
                "live extreme",
                "benefit man",
                "work man",
                "social service",
                "help woman",
                "economic resource",
                "vulnerable population",
                "home care",
                "vulnerable group",
                "national local",
                "social protection programme",
                "family child",
                "market opportunity",
                "vulnerable employment",
                "protection programme",
                "service provide",
                "low rate",
                "gender sensitive",
                "public spending",
                "country reduce",
                "child impact",
                "benefit poor",
                "poverty extreme",
                "household poverty",
                "rural urban",
                "indigenous community",
                "poverty extreme poverty",
                "social care",
                "poor benefit",
                "disposable income",
                "energy policy",
                "trade integration",
                "policy making",
                "stabilisation policy",
                "avoid negative",
                "health education",
                "provide poor"
            ]
        },
        {
            "sdg": 2,
            "importance": 0.1328540457393524,
            "category": "low",
            "features": [
                "food insecurity",
                "food security",
                "food consumption",
                "poor household",
                "food price",
                "country experience",
                "high incidence poverty",
                "child experience",
                "agricultural research",
                "agricultural productivity",
                "food production",
                "agricultural production",
                "poverty rate",
                "poverty threshold",
                "poverty hunger",
                "land reform",
                "agricultural practice",
                "water policy",
                "time poverty",
                "fertiliser subsidy",
                "food trade",
                "customary law",
                "agricultural development",
                "rural poverty",
                "ministry agency",
                "rate poverty",
                "fishery product",
                "lack access",
                "give poverty",
                "poverty gap",
                "rate figure",
                "hunger malnutrition",
                "proportion undernourished",
                "gender relate",
                "food safety",
                "multidimensional poverty",
                "child country",
                "prevalence undernourishment",
                "minimum income",
                "trade remain",
                "undernourished people",
                "practice sustainable",
                "large exporter",
                "sustainable agriculture",
                "child malnutrition",
                "plant base",
                "death child",
                "growth performance",
                "time poverty threshold",
                "raise agricultural productivity"
            ]
        },
        {
            "sdg": 3,
            "importance": 0.6457096275052352,
            "category": "medium",
            "features": [
                "public health",
                "young people",
                "health care system",
                "people age",
                "care system",
                "high rate",
                "mental health",
                "family planning",
                "health service",
                "health expenditure",
                "high risk",
                "traffic accident",
                "reproductive health",
                "infant mortality",
                "mortality rate",
                "policy action",
                "post conflict",
                "time high",
                "lack capacity",
                "make process",
                "low middle income",
                "ensure woman",
                "access land",
                "people live",
                "human development",
                "high prevalence",
                "section review",
                "life expectancy",
                "policy need",
                "share country",
                "cent cent",
                "health insurance",
                "early pregnancy",
                "contraceptive use",
                "health outcome",
                "health risk",
                "health spending",
                "live birth",
                "sexual reproductive",
                "sexual reproductive health",
                "infectious disease",
                "universal health",
                "road traffic",
                "premature death",
                "account case",
                "road traffic accident",
                "overweight obesity",
                "health inequality",
                "policy social protection",
                "health sector"
            ]
        },
        {
            "sdg": 4,
            "importance": 0.45527423992586724,
            "category": "medium",
            "features": [
                "primary school",
                "care practice",
                "secondary level",
                "access education",
                "early childhood education",
                "childhood education",
                "education institution",
                "school attendance",
                "basic education",
                "primary education",
                "early childhood",
                "secondary education",
                "secondary school",
                "provide education",
                "high education",
                "income high",
                "complete secondary education",
                "structural transformation",
                "reduce child",
                "use fund",
                "high education institution",
                "improve health",
                "work experience",
                "work life",
                "education policy",
                "school enrolment",
                "tertiary education",
                "literacy skill",
                "teacher education",
                "education reform",
                "household composition",
                "education quality",
                "young child",
                "school evaluation",
                "training education",
                "learning opportunity",
                "literacy numeracy",
                "public school",
                "number challenge",
                "age population",
                "find job",
                "student school",
                "vocational training",
                "score average",
                "educational inequality",
                "social economic",
                "figure total",
                "completion rate",
                "education information",
                "school student"
            ]
        },
        {
            "sdg": 5,
            "importance": 0.5152556062051462,
            "category": "medium",
            "features": [
                "man woman",
                "female male",
                "sexual violence",
                "gender inequality",
                "domestic violence",
                "gender mainstreaming",
                "employment rate",
                "violence woman",
                "gender equality",
                "social inclusion",
                "migrant woman",
                "poor family",
                "individual level",
                "income poor",
                "special measure",
                "age income",
                "goal achieve",
                "cent woman",
                "rate high",
                "good service",
                "mean test",
                "young woman",
                "alcohol consumption",
                "role responsibility",
                "equal opportunity",
                "country report",
                "enrolment rate",
                "female employment",
                "child marriage",
                "gender gap",
                "gender parity",
                "gender discrimination",
                "woman entrepreneur",
                "woman right",
                "economic participation",
                "force marriage",
                "gender segregation",
                "equal access",
                "woman country",
                "increase female",
                "issue gender",
                "promote gender",
                "high woman",
                "time use",
                "country lag",
                "include gender",
                "woman girl",
                "man age",
                "woman woman",
                "woman high"
            ]
        },
        {
            "sdg": 6,
            "importance": 0.08189334063440692,
            "category": "low",
            "features": [
                "past year",
                "water supply",
                "water management",
                "policy framework",
                "water user",
                "cost water",
                "drinking water",
                "country agricultural",
                "population access",
                "risk high",
                "pollution river",
                "water quality",
                "improvement water",
                "social cultural",
                "efficient use",
                "energy sector",
                "water sanitation facility",
                "government department",
                "self report",
                "farmer receive",
                "financial incentive",
                "information communication",
                "rural area",
                "water pricing",
                "level population",
                "cost investment",
                "agricultural policy",
                "system level",
                "opportunity cost",
                "cent total",
                "past decade",
                "woman unpaid",
                "environmental quality",
                "water scarcity",
                "wastewater treatment",
                "water use",
                "water sanitation",
                "water resource",
                "water allocation",
                "water resource management",
                "resource management",
                "water service",
                "zone area",
                "flood protection",
                "water right",
                "total water",
                "sanitation facility",
                "river basin",
                "clean water",
                "provide water"
            ]
        },
        {
            "sdg": 7,
            "importance": 0.5948523789107033,
            "category": "medium",
            "features": [
                "renewable energy",
                "electricity generation",
                "energy project",
                "improve energy efficiency",
                "improve energy",
                "energy efficiency",
                "energy consumption",
                "sustainable energy",
                "solar power",
                "energy use",
                "efficiency standard",
                "renewable electricity",
                "renewable energy project",
                "petroleum product",
                "region project",
                "potential reduce",
                "energy supply",
                "smart grid",
                "energy infrastructure",
                "energy transition",
                "energy saving",
                "energy need",
                "power plant",
                "impact climate change",
                "impact climate",
                "rural electrification",
                "develop country account",
                "slow growth",
                "multilateral climate",
                "productive activity",
                "country similar",
                "new technology",
                "sustainability criterion",
                "fishing sector",
                "energy price",
                "country figure",
                "compare cent",
                "active role",
                "gender responsive",
                "increase price",
                "energy security",
                "energy intensity",
                "nuclear power",
                "district heating",
                "energy conservation",
                "energy access",
                "gender disaggregate",
                "year plan",
                "access electricity",
                "electric vehicle"
            ]
        },
        {
            "sdg": 8,
            "importance": 0.9376823051832879,
            "category": "high",
            "features": [
                "economic growth",
                "labour force",
                "economic development",
                "income country",
                "trade investment",
                "country high",
                "global financial",
                "programme design",
                "child labour",
                "woman access",
                "agricultural sector",
                "figure high",
                "country woman",
                "asian country",
                "year age",
                "woman entrepreneurship",
                "level education",
                "high quality",
                "labour productivity",
                "labour market",
                "rate growth",
                "growth create",
                "financial crisis",
                "live rural area",
                "woman year",
                "national average",
                "educational level",
                "low carbon",
                "science technology",
                "educational achievement",
                "tourism sector",
                "improve performance",
                "ill health",
                "pay work",
                "productivity growth",
                "likely work",
                "average wage",
                "address issue",
                "compare country",
                "sector cover",
                "work programme",
                "food processing",
                "social impact",
                "green economy",
                "region term",
                "report note",
                "financial support",
                "informal economy",
                "medium term",
                "digital economy"
            ]
        },
        {
            "sdg": 9,
            "importance": 0.5656844353332069,
            "category": "medium",
            "features": [
                "develop economy",
                "financial flow",
                "access high",
                "low level",
                "development plan",
                "start up",
                "datum available",
                "world market",
                "build consensus",
                "trade reform",
                "achieve target",
                "small state",
                "support mechanism",
                "female entrepreneur",
                "information provide",
                "domestic market",
                "health system",
                "ministry charge",
                "efficiency gain",
                "compare average",
                "measure include",
                "health condition",
                "like thank",
                "education training",
                "achieve sdg",
                "international market",
                "mobile phone",
                "product service",
                "political party",
                "include woman",
                "central local",
                "social innovation",
                "infrastructure investment",
                "investment need",
                "value chain",
                "water authority",
                "service delivery",
                "quality water",
                "final demand",
                "low skilled",
                "export market",
                "legal framework",
                "country provide",
                "exchange rate",
                "public infrastructure",
                "positive effect",
                "progress achieve",
                "internet access",
                "road infrastructure",
                "trade off"
            ]
        },
        {
            "sdg": 10,
            "importance": 0.2781324627695611,
            "category": "medium",
            "features": [
                "development finance",
                "develop country",
                "development strategy",
                "education health",
                "service sector",
                "interest rate",
                "contribute social",
                "small business",
                "country average",
                "control resource",
                "inequality country",
                "gender relation",
                "income distribution",
                "care need",
                "global inequality",
                "reduce child poverty",
                "woman economic empowerment",
                "economic empowerment",
                "woman economic",
                "country country",
                "macro economic",
                "large contribution",
                "similar measure",
                "child right",
                "cross border",
                "poverty figure",
                "help farmer",
                "regional development",
                "age group",
                "country available",
                "market access",
                "broad development",
                "education skill",
                "tax revenue",
                "woman represent",
                "emerge economy",
                "head household",
                "poverty affect",
                "destination country",
                "have child",
                "community include",
                "developed country",
                "national regional",
                "official statistic",
                "policy measure",
                "regional level",
                "country develop",
                "transport sector",
                "access opportunity",
                "likely increase"
            ]
        },
        {
            "sdg": 11,
            "importance": 0.8421373004720891,
            "category": "high",
            "features": [
                "high cost",
                "urban area",
                "community base",
                "line ministry",
                "natural disaster",
                "woman labour",
                "commercial industrial",
                "impact poverty",
                "national level",
                "average household",
                "service provision",
                "urban rural area",
                "rural development",
                "technical assistance",
                "population growth",
                "household income",
                "urban rural",
                "development policy",
                "climate change adaptation",
                "infrastructure development",
                "local government",
                "economic social",
                "report number",
                "low productivity",
                "old age",
                "term growth",
                "knowledge technology",
                "economic efficiency",
                "social housing",
                "employ worker",
                "action plan",
                "attendance rate",
                "immigrant student",
                "world population",
                "minority group",
                "community development",
                "cross country",
                "hydropower plant",
                "support implementation",
                "disaster risk",
                "build resilience",
                "country water",
                "infrastructure electricity",
                "irrigate land",
                "electricity gas",
                "co ordinate",
                "civil society",
                "change impact",
                "public work",
                "population density"
            ]
        },
        {
            "sdg": 12,
            "importance": 0.22565526581584408,
            "category": "low",
            "features": [
                "private sector",
                "fuel subsidy",
                "well utilisation",
                "important challenge",
                "low income",
                "aquaculture production",
                "woman affect",
                "resource efficiency",
                "average real",
                "household waste",
                "land water",
                "national legislation",
                "make difference",
                "spatial planning",
                "area include",
                "large quantity",
                "efficiency conservation",
                "aim assist",
                "air water",
                "public procurement",
                "member state",
                "post harvest",
                "production trade",
                "institution include",
                "waste management",
                "cent energy",
                "solid waste",
                "natural resource",
                "waste collection",
                "environmental sustainability",
                "resource use",
                "previous decade",
                "place economic",
                "policy policy",
                "subsidy reform",
                "reduce increase",
                "waste generation",
                "waste disposal",
                "consumption level",
                "sustainable management",
                "sustainable production",
                "waste collect",
                "dairy farming",
                "water groundwater",
                "household consumption",
                "consumer behaviour",
                "hazardous waste",
                "environmental pollution",
                "food waste",
                "circular economy"
            ]
        },
        {
            "sdg": 13,
            "importance": 1.0,
            "category": "high",
            "features": [
                "climate change",
                "climate finance",
                "long term",
                "production increase",
                "provision basic service",
                "air pollution",
                "increase share",
                "national policy",
                "wind power",
                "carbon economy",
                "low carbon economy",
                "development partner",
                "climate resilience",
                "diffuse source",
                "water high",
                "job create",
                "range different",
                "estimate base",
                "environmental issue",
                "health social",
                "national law",
                "public good",
                "majority population",
                "review report",
                "provide usd",
                "new market",
                "high price",
                "project developer",
                "economic sector",
                "carbon tax",
                "carbon pricing",
                "global warming",
                "human resource",
                "measurement reporting",
                "sub national",
                "introduction new",
                "overall development",
                "trade barrier",
                "greenhouse gas",
                "gas emission",
                "environment climate",
                "disaster risk management",
                "result research",
                "finance include",
                "reduce greenhouse gas",
                "reduce greenhouse",
                "mitigation adaptation",
                "climate policy",
                "change mitigation",
                "climate change mitigation"
            ]
        },
        {
            "sdg": 14,
            "importance": 0.04017458176214876,
            "category": "low",
            "features": [
                "consumer education",
                "small producer",
                "small scale",
                "fishery subsidy",
                "negative impact",
                "strength weakness",
                "monitor evaluate",
                "business model",
                "global economy",
                "general service",
                "nordic country",
                "country region",
                "local community",
                "coastal zone",
                "increase water",
                "coastal water",
                "water storage",
                "large scale",
                "instal capacity",
                "general public",
                "domestic use",
                "estimate usd",
                "direct access",
                "economic benefit",
                "main policy",
                "non consumptive",
                "region include",
                "zone measure",
                "trade country",
                "world poor",
                "early warning",
                "rapid growth",
                "governance approach",
                "management system",
                "problem relate",
                "measure reduce",
                "report indigenous",
                "coastal marine",
                "marine pollution",
                "marine environment",
                "ocean resource",
                "effectiveness principle",
                "resource recognize",
                "fish specie",
                "marine ecosystem",
                "reduce nutrient",
                "fishery sector",
                "status early",
                "unreported fishing",
                "tsunami early warning"
            ]
        },
        {
            "sdg": 15,
            "importance": 0.18274568742715117,
            "category": "low",
            "features": [
                "land use",
                "protect area",
                "access basic",
                "use right",
                "add value",
                "infrastructure service",
                "land registration",
                "role agriculture",
                "sea level",
                "reduce emission",
                "use land",
                "food grain",
                "fuel wood",
                "co ordination",
                "biomass production",
                "high level",
                "construction new",
                "people increase",
                "average year",
                "drought flood",
                "water body",
                "significant negative",
                "regional plan",
                "urban policy",
                "source include",
                "mitigation activity",
                "environmental problem",
                "energy market",
                "national international",
                "own enterprise",
                "agriculture water",
                "level government",
                "long term sustainable",
                "term sustainable",
                "fall cent",
                "product process",
                "exist market",
                "new development",
                "state budget",
                "aquatic environment",
                "government establish",
                "indigenous population",
                "set indicator",
                "surface water",
                "invasive specie",
                "economic value",
                "provide input",
                "new water",
                "increase area",
                "forest area"
            ]
        },
        {
            "sdg": 16,
            "importance": 0.778626015481794,
            "category": "high",
            "features": [
                "central government",
                "public sector",
                "measure place",
                "decision making",
                "economic policy",
                "decision make",
                "individual country",
                "public policy",
                "national income",
                "country prepare",
                "young girl",
                "woman time",
                "law policy",
                "government people",
                "non governmental",
                "end child",
                "education develop",
                "policy ensure",
                "human right",
                "country introduce",
                "high wage",
                "parental leave",
                "power relation",
                "support project",
                "physical infrastructure",
                "country need",
                "help identify",
                "job opportunity",
                "policy challenge",
                "increase capacity",
                "local authority",
                "family community",
                "government set",
                "realize potential",
                "major city",
                "policy practice",
                "proportion female",
                "minimum level",
                "neighbouring country",
                "project develop",
                "adverse impact",
                "economy grow",
                "regulatory system",
                "good governance",
                "km3 year",
                "international cooperation",
                "law enforcement",
                "water governance",
                "inclusive society",
                "transparency accountability"
            ]
        },
        {
            "sdg": 17,
            "importance": 0.045980335034502454,
            "category": "low",
            "features": [
                "public private",
                "private partnership",
                "public private partnership",
                "sustainable development",
                "development goal",
                "monitoring evaluation",
                "evidence base",
                "subsidy transfer",
                "support development",
                "good practice",
                "transaction cost",
                "great emphasis",
                "potential contribute",
                "place great emphasis",
                "place great",
                "investment infrastructure",
                "management approach",
                "risk management",
                "public investment",
                "fish world",
                "national definition",
                "market share",
                "large project",
                "budgetary expenditure",
                "attract private investment",
                "priority area",
                "local development",
                "wide benefit",
                "limited datum",
                "open inclusive",
                "market country",
                "ongoing initiative",
                "include recent",
                "foreign aid",
                "informal sector",
                "mainstreame development",
                "woman business",
                "available datum",
                "improve effectiveness",
                "partnership agreement",
                "government private",
                "government private sector",
                "sdg national",
                "agreement include",
                "effectiveness public",
                "datum gap",
                "evidence base policy",
                "base policy",
                "finance available",
                "financing need"
            ]
        }
    ],
    "strategy": "equal",
    "doc_count_total": 10,
    "doc_count_valid": 10,
    "doc_name": [
        {
            "name": "Disaster Risk Financing Policy 2022 - 2025 ",
            "link": ""
        },
        {
            "name": "Fiscal Strategy Statement FY2023/2024 Main Estimates",
            "link": ""
        },
        {
            "name": "Health Sector Plan 2019/20-2029/30",
            "link": ""
        },
        {
            "name": "Pathway for the Development of Samoa FY2021/22-FY2025/26",
            "link": ""
        },
        {
            "name": "2022 Development Finance Assessment ",
            "link": ""
        },
        {
            "name": "2021/22 Pacific Attitudes Survey: Samoa",
            "link": ""
        },
        {
            "name": "2020 Education Sector COVID Response Plan",
            "link": ""
        },
        {
            "name": "2021 Samoa's Nationally Determined Contribution  Implementation Roadmap and Investment Plan",
            "link": ""
        },
        {
            "name": "Samoa Low Emission Strategy 2021-2030",
            "link": ""
        },
        {
            "name": "2022 Gender Equality Brief for Samoa",
            "link": ""
        }
    ]
}